duppla_aws/__init__.py
duppla_aws/py.typed
duppla_aws/constants/__init__.py
duppla_aws/constants/py.typed
duppla_aws/models/__init__.py
duppla_aws/models/py.typed
duppla_aws/service/__init__.py
duppla_aws/service/_cloudformation.py
duppla_aws/service/_cloudwatchlog.py
duppla_aws/service/_dynamodb.py
duppla_aws/service/_glacier.py
duppla_aws/service/_iam.py
duppla_aws/service/_opsworks.py
duppla_aws/service/_s3.py
duppla_aws/service/_ses.py
duppla_aws/service/_sns.py
duppla_aws/service/_sqs.py
duppla_aws/service/public.py
duppla_aws/service/py.typed
duppla_aws/utils/__init__.py
duppla_aws/utils/encoder.py
duppla_aws/utils/py.typed
duppla_aws-2025.12.9.14.56.dist-info/licenses/LICENSE
duppla_aws-2025.12.9.14.56.dist-info/METADATA
duppla_aws-2025.12.9.14.56.dist-info/WHEEL
duppla_aws-2025.12.9.14.56.dist-info/top_level.txt
duppla_aws-2025.12.9.14.56.dist-info/RECORD
