Metadata-Version: 2.4
Name: duppla_aws
Version: 2025.12.9.14.56
Summary: Custom implementation for the AWS resources
Author: duppla
Author-email: <>
Keywords: python,aws,duppla
Classifier: Development Status :: 1 - Planning
Classifier: Intended Audience :: Developers
Classifier: Programming Language :: Python :: 3
Classifier: Operating System :: Unix
Classifier: Operating System :: MacOS :: MacOS X
Classifier: Operating System :: Microsoft :: Windows
License-File: LICENSE
Requires-Dist: pydantic<3.0.0,>=2.7.0
Requires-Dist: pydantic_extra_types
Requires-Dist: boto3>=1.37.4
Dynamic: author
Dynamic: author-email
Dynamic: classifier
Dynamic: description
Dynamic: description-content-type
Dynamic: keywords
Dynamic: license-file
Dynamic: requires-dist
Dynamic: summary
